client/__init__.py
client/data_manager.py
client/menu.py
client/menu_enum.py
client/panel.py
pyspotify_client-0.0.1.dist-info/LICENSE
pyspotify_client-0.0.1.dist-info/METADATA
pyspotify_client-0.0.1.dist-info/WHEEL
pyspotify_client-0.0.1.dist-info/top_level.txt
pyspotify_client-0.0.1.dist-info/RECORD
