Metadata-Version: 2.1
Name: pyspotify-client
Version: 0.0.1
Summary: Python package to remotely access your spotify account.
Home-page: https://github.com/Bnjorogedev/pyspotify-client
Author: Bill
Author-email: williamsriunge@gmail.com
License: UNKNOWN
Platform: UNKNOWN
Classifier: Programming Language :: Python :: 3
Classifier: License :: OSI Approved :: MIT License
Classifier: Operating System :: OS Independent
Requires-Python: >=3.6
